django_cached_functions.py
setup.py
django_cached_functions.egg-info/PKG-INFO
django_cached_functions.egg-info/SOURCES.txt
django_cached_functions.egg-info/dependency_links.txt
django_cached_functions.egg-info/top_level.txt