Metadata-Version: 1.0
Name: django-cached-functions
Version: 0.1.1
Summary: Prevent expensive computations by storing low level calues in the django cache
Home-page: UNKNOWN
Author: Rory McCann
Author-email: rory@technomancy.org
License: GPLv3
Platform: UNKNOWN
